{
  "products": [
    { "id": 1, "title": "product 1","img":"05f4d162744461.Y3JvcCw3MzAwLDU3MTQsMzYwLDA.jpg" },
    { "id": 2, "title": "product 2","img":"07ae8690034587.Y3JvcCwxNjE2LDEyNjQsMCww.gif" },
    { "id": 3, "title": "product 3","img":"0bc3df90611285.Y3JvcCwxMzM0LDEwNDMsMjksNjA0.jpg" },
    { "id": 4, "title": "product 4","img":"0dac7778693947.Y3JvcCw5NjYsNzU2LDksMzU0.jpg" },
    { "id": 5, "title": "product 5","img":"0e1f9e90641063.Y3JvcCwzMjkzLDI1NzYsNjUyLDA.jpg" },
    { "id": 6, "title": "product 6","img":"05f4d162744461.Y3JvcCw3MzAwLDU3MTQsMzYwLDA.jpg" },
    { "id": 7, "title": "product 7","img":"0e31fd90431257.Y3JvcCwyMDA1LDE1NjgsNjc1LDI5Mg.jpg" },
    { "id": 8, "title": "product 8","img":"11bd1d88583875.Y3JvcCwxMTA2LDg2NSw5Myw2MA.jpg" },
    { "id": 9, "title": "product 9","img":"134c2e79682943.Y3JvcCwxMDgwLDg0NCwwLDA.jpg" },
    { "id": 10, "title": "product 10","img":"1a28fb90199071.Y3JvcCwzNTYwLDI3ODUsMTQ5LDIwMg.jpg" },
    { "id": 11, "title": "product 11","img":"1fa57b90724085.Y3JvcCw4NzAsNjgwLDEwNywxODU.jpg" },
    { "id": 12, "title": "product 12","img":"1fda7090885269.Y3JvcCw5NjAsNzUwLDAsMjI1.jpg" },
    { "id": 13, "title": "product 13","img":"2f19a089266221.Y3JvcCwzNjE0LDI4MjYsMCw4NTg.jpg" },
    { "id": 14, "title": "product 14","img":"34091861723333.Y3JvcCwxNTQyLDEyMDcsMzQ2LDIy.jpg" },
    { "id": 15, "title": "product 15","img":"3c35ea90483867.Y3JvcCwxNTUxLDEyMTMsOTYsMjQ5.jpg" },
    { "id": 16, "title": "product 16","img":"3f534490706373.Y3JvcCwyMDY3LDE2MTYsMjgxLDIyMA.png" },
    { "id": 17, "title": "product 17","img":"4334b864035821.Y3JvcCwxMTkzLDkzMywxMDYsMA.jpg" },
    { "id": 18, "title": "product 18","img":"44666c90030299.Y3JvcCw5MjQsNzIzLDIzNSwxOA.jpg" },
    { "id": 19, "title": "product 19","img":"44e8df62635413.Y3JvcCw4MDgsNjMyLDAsMA.png" },
    { "id": 20, "title": "product 20","img":"44f6cf90916633.Y3JvcCwxMDg2LDg1MCwyNCww.jpg" },
    { "id": 21, "title": "product 21","img":"47bc8f90847977.Y3JvcCwxMTk1LDkzNSw5Nyww.jpg" },
    { "id": 22, "title": "product 22","img":"4a047c89947875.Y3JvcCw1ODAwLDQ1MzYsMCw2MzE.png" },
    { "id": 23, "title": "product 23","img":"4a24e690420163.Y3JvcCwxNDAwLDEwOTUsMCww.jpg" },
    { "id": 24, "title": "product 24","img":"4cc43490678457.Y3JvcCw0Nzk0LDM3NTAsMTA2LDA.jpg" },
    { "id": 25, "title": "product 25","img":"4da9b190311259.Y3JvcCwxMjQ1LDk3NCwxODgsNDY.jpg" },
    { "id": 26, "title": "product 26","img":"4fe60a90842481.Y3JvcCwzNjQzLDI4NDksMCw0MjM.jpg" },
    { "id": 27, "title": "product 27","img":"51514f91156539.Y3JvcCw5MjAsNzIwLDEzOCww.jpg" },
    { "id": 28, "title": "product 28","img":"57824b89340115.Y3JvcCwxNDA4LDExMDIsNTMzLDA.jpg" },
    { "id": 29, "title": "product 29","img":"59cd9390457675.Y3JvcCwxMDUwLDgyMSwxMjksMA.jpg" },
    { "id": 30, "title": "product 30","img":"5a5d4f84974155.Y3JvcCwxMjU0LDk4MSw3NCw1NQ.png" },
    { "id": 31, "title": "product 31","img":"64515b90811515.Y3JvcCwxOTk5LDE1NjQsMCw3MTc.jpg" },
    { "id": 32, "title": "product 32","img":"685e7891092987.Y3JvcCw4MDgsNjMyLDAsMA.jpg" },
    { "id": 33, "title": "product 33","img":"701c1489980289.Y3JvcCwyNDg5LDE5NDcsNTExLDI2NA.jpg" },
    { "id": 34, "title": "product 34","img":"73df9790652937.Y3JvcCwyODMyLDIyMTUsMTI2LDEwNQ.jpg" },
    { "id": 35, "title": "product 35","img":"746d6d90313877.Y3JvcCwxNDQyLDExMjcsMCww.png" },
    { "id": 36, "title": "product 36","img":"775ea162664731.Y3JvcCwxNjAzLDEyNTUsMCwxMDI.jpg" },
    { "id": 37, "title": "product 37","img":"77690990722101.Y3JvcCw5OTksNzgyLDAsMA.jpg" },
    { "id": 38, "title": "product 38","img":"77bd0689930317.Y3JvcCw4MDgsNjMyLDAsMA.jpg" },
    { "id": 39, "title": "product 39","img":"7a6a6e90493009.Y3JvcCw5ODIsNzY4LDIxOCwxNjI.jpg" },
    { "id": 40, "title": "product 40","img":"82a27390100689.Y3JvcCw0MDE5LDMxNDMsNTg2LDY5.jpg" },
    { "id": 41, "title": "product 41","img":"84633480_183131466093679_5585075261541449728_n.jpg" },
    { "id": 42, "title": "product 42","img":"8bdbf276543531.Y3JvcCwxMDIyLDgwMCw4Myww.jpg" },
    { "id": 43, "title": "product 43","img":"912d1c89802995.Y3JvcCwxNTk2LDEyNDksMzgzLDA.png" },
    { "id": 44, "title": "product 44","img":"58e8190488701.Y3JvcCw4OTcsNzAxLDEyNiw0Mg.jpg" },
    { "id": 45, "title": "product 45","img":"984f9b89918395.Y3JvcCw1MTEzLDQwMDAsNzU5LDA.jpg" },
    { "id": 46, "title": "product 46","img":"9a3a1256288763.Y3JvcCwxMjAwLDkzOCwwLDEzMA.jpg" },
    { "id": 47, "title": "product 47","img":"9d43ad86908395.Y3JvcCwxMjc4LDEwMDAsNjAsMA.jpg" },
    { "id": 48, "title": "product 48","img":"a0c56d90332183.Y3JvcCwzMDE1LDIzNTksODIsMA.jpg" },
    { "id": 49, "title": "product 49","img":"a0cabe90070949.Y3JvcCw4ODYsNjkzLDE2NiwxODg.jpg" },
    { "id": 50, "title": "product 50","img":"a70d8b82997643.Y3JvcCw5NjIsNzUyLDAsMjIx.jpg" },
    { "id": 52, "title": "product 51","img":"aa841e66575395.Y3JvcCwxOTI0LDE1MDYsMCwxOQ.jpg" },
    { "id": 53, "title": "product 53","img":"b2a2c189853285.Y3JvcCw4MDgsNjMyLDAsMA.jpg" },
    { "id": 54, "title": "product 54","img":"b89ef888315201.Y3JvcCwxMzMzLDEwNDIsMCwzMTM.jpg" },
    { "id": 55, "title": "product 55","img":"b9333764092647.Y3JvcCw4MDgsNjMyLDAsMA.jpg" },
    { "id": 56, "title": "product 56","img":"bb5ad264396475.Y3JvcCwxMTIxLDg3NywxNDEsMA.jpg" },
    { "id": 57, "title": "product 57","img":"bda19283960543.Y3JvcCwxOTk5LDE1NjQsMCw0NzA.jpg" },
    { "id": 58, "title": "product 58","img":"c01e1790602411.Y3JvcCwzMzQwLDI2MTMsNTU0LDA.jpg" },
    { "id": 59, "title": "product 59","img":"c1399482152085.Y3JvcCwxODgxLDE0NzEsMzcyLDI1Ng.jpg" },
    { "id": 60, "title": "product 60","img":"c2c00290965379.Y3JvcCwxNjE2LDEyNjQsMCww.jpg" },
    { "id": 61, "title": "product 61","img":"c744d090328207.Y3JvcCw4MDgsNjMyLDAsMA.png" },
    { "id": 62, "title": "product 62","img":"c8ad7e90688501.Y3JvcCw4MDgsNjMyLDAsMA.png" },
    { "id": 63, "title": "product 63","img":"cba1c190145119.Y3JvcCwxMTIzLDg3OCwxMzgsNTU.jpg" },
    { "id": 64, "title": "product 64","img":"cea35790781741.Y3JvcCwyMDQ1LDE2MDAsNDMwLDA.jpg" },
    { "id": 65, "title": "product 65","img":"d34a0190626287.Y3JvcCwyNjA5LDIwNDAsNjMyLDEwOQ.jpg" },
    { "id": 66, "title": "product 66","img":"dccc9c90424079.Y3JvcCw4MDgsNjMyLDAsMA.png" },
    { "id": 67, "title": "product 67","img":"ddb08a90596515.Y3JvcCwxMTA3LDg2NiwxMDEsMTk.jpg" },
    { "id": 68, "title": "product 68","img":"e7fb5a89685437.Y3JvcCwxNDk5LDExNzMsMzcsMA.jpg" },
    { "id": 69, "title": "product 69","img":"e94a1689424003.Y3JvcCwyMTMxLDE2NjcsMTg0LDA.jpg" },
    { "id": 70, "title": "product 70","img":"ea6b6660669711.Y3JvcCwxMTkxLDkzMiw5MSww.jpg" },
    { "id": 71, "title": "product 71","img":"ed5a2d90077439.Y3JvcCwyMTMzLDE2NjgsMCwxMTE5.jpg" },
    { "id": 72, "title": "product 72","img":"f7537091162831.Y3JvcCwxMDE0LDc5MywxOTUsMTI1.jpg" },
    { "id": 73, "title": "product 73","img":"f9fe1890229713.Y3JvcCwxNjM2LDEyODAsMTMzLDA.jpg" }
  ]
}
